{
  "scriptId": "332",
  "url": "file:///Users/dvorson/Projects/dvorson.github.io/admin/tests/api_endpoints_test.ts",
  "functions": [
    {
      "functionName": "",
      "ranges": [{ "startOffset": 0, "endOffset": 4333, "count": 1 }],
      "isBlockCoverage": true
    },
    {
      "functionName": "createMockRequest",
      "ranges": [{ "startOffset": 256, "endOffset": 555, "count": 4 }],
      "isBlockCoverage": true
    },
    {
      "functionName": "setupFilesystemMocks",
      "ranges": [{ "startOffset": 771, "endOffset": 1080, "count": 4 }],
      "isBlockCoverage": true
    },
    {
      "functionName": "",
      "ranges": [{ "startOffset": 877, "endOffset": 898, "count": 0 }],
      "isBlockCoverage": false
    },
    {
      "functionName": "",
      "ranges": [{ "startOffset": 971, "endOffset": 996, "count": 0 }],
      "isBlockCoverage": false
    },
    {
      "functionName": "",
      "ranges": [{ "startOffset": 1055, "endOffset": 1076, "count": 0 }],
      "isBlockCoverage": false
    },
    {
      "functionName": "restoreFilesystemMocks",
      "ranges": [{ "startOffset": 1081, "endOffset": 1370, "count": 4 }],
      "isBlockCoverage": true
    },
    {
      "functionName": "",
      "ranges": [{ "startOffset": 1414, "endOffset": 2293, "count": 1 }],
      "isBlockCoverage": true
    },
    {
      "functionName": "render",
      "ranges": [{ "startOffset": 1788, "endOffset": 1806, "count": 0 }],
      "isBlockCoverage": false
    },
    {
      "functionName": "",
      "ranges": [{ "startOffset": 2344, "endOffset": 3223, "count": 1 }],
      "isBlockCoverage": true
    },
    {
      "functionName": "render",
      "ranges": [{ "startOffset": 2716, "endOffset": 2734, "count": 0 }],
      "isBlockCoverage": false
    },
    {
      "functionName": "",
      "ranges": [{ "startOffset": 3279, "endOffset": 3774, "count": 1 }],
      "isBlockCoverage": true
    },
    {
      "functionName": "render",
      "ranges": [{ "startOffset": 3551, "endOffset": 3569, "count": 0 }],
      "isBlockCoverage": false
    },
    {
      "functionName": "",
      "ranges": [{ "startOffset": 3832, "endOffset": 4330, "count": 1 }],
      "isBlockCoverage": true
    },
    {
      "functionName": "render",
      "ranges": [{ "startOffset": 4105, "endOffset": 4123, "count": 0 }],
      "isBlockCoverage": false
    }
  ]
}
